.gitignore
LICENSE
README.md
_config.yml
setup.py
stroop/__init__.py
stroop/stimulus.py
stroop.egg-info/PKG-INFO
stroop.egg-info/SOURCES.txt
stroop.egg-info/dependency_links.txt
stroop.egg-info/not-zip-safe
stroop.egg-info/requires.txt
stroop.egg-info/top_level.txt