Metadata-Version: 1.0
Name: stroop
Version: 0.3
Summary: a package for stroop stimuli
Home-page: https://github.com/qihongl/stroop-stimuli
Author: Qihong Lu
Author-email: qlu@princeton.edu
License: MIT
Keywords: cognitive science
Platform: UNKNOWN
